dipl/__init__.py
dipl/dipl.py
dipl-1.1.0.dist-info/METADATA
dipl-1.1.0.dist-info/WHEEL
dipl-1.1.0.dist-info/licenses/LICENSE
dipl-1.1.0.dist-info/RECORD
