Metadata-Version: 2.1
Name: dipl
Version: 1.1.0
Summary: Python reader and parser module for DIP language
Project-URL: Homepage, https://github.com/vrtulka23/dipl
Project-URL: Bug Tracker, https://github.com/vrtulka23/dipl/issues
Author-email: Ondrej Pego Jaura <vrtulka23@pm.me>
License-File: LICENSE
Classifier: License :: OSI Approved :: MIT License
Classifier: Operating System :: OS Independent
Classifier: Programming Language :: Python :: 3
Requires-Python: >=3.7
